[
  {
    "line": 2,
    "elements": [
      {
        "before": [
          {
            "result": {
              "duration": 5228306045,
              "status": "passed"
            },
            "match": {
              "location": "GoogleSearch.setUp(Scenario)"
            }
          }
        ],
        "line": 5,
        "name": "verify home navbar menuitem visible in homepage",
        "description": "",
        "id": "oti-homepage-validation;verify-home-navbar-menuitem-visible-in-homepage",
        "after": [
          {
            "result": {
              "duration": 397940017,
              "status": "passed"
            },
            "match": {
              "location": "GoogleSearch.teardown(Scenario)"
            }
          }
        ],
        "type": "scenario",
        "keyword": "Scenario",
        "steps": [
          {
            "result": {
              "duration": 18274485585,
              "status": "passed"
            },
            "line": 6,
            "name": "a visitor to OTI hompage using desktop browser",
            "match": {
              "location": "homePage.a_visitor_to_OTI_hompage_using_desktop_browser()"
            },
            "keyword": "Given "
          },
          {
            "result": {
              "duration": 420481030,
              "status": "passed"
            },
            "line": 7,
            "name": "the Home nevbar menuitem is visible",
            "match": {
              "location": "homePage.the_Home_nevbar_is_visible()"
            },
            "keyword": "Then "
          },
          {
            "result": {
              "duration": 20494190,
              "status": "passed"
            },
            "line": 8,
            "name": "the \u0027View courses\u0027 nevbar menuitem is visible",
            "match": {
              "location": "homePage.the_View_courses_nevbar_menuitem_is_visible()"
            },
            "keyword": "Then "
          },
          {
            "result": {
              "duration": 22656921,
              "status": "passed"
            },
            "line": 9,
            "name": "the \u0027Study online\u0027 nevbar menuitem is visible",
            "match": {
              "location": "homePage.the_Study_online_nevbar_menuitem_is_visible()"
            },
            "keyword": "Then "
          },
          {
            "result": {
              "duration": 13797417,
              "status": "passed"
            },
            "line": 10,
            "name": "the \u0027How we support you\u0027 nevbar menuitem is visible",
            "match": {
              "location": "homePage.the_How_we_support_you_nevbar_menuitem_is_visible()"
            },
            "keyword": "Then "
          },
          {
            "result": {
              "duration": 14352211,
              "status": "passed"
            },
            "line": 11,
            "name": "the \u0027Study online\u0027 nevbar menuitem is visible",
            "match": {
              "location": "homePage.the_Study_online_nevbar_menuitem_is_visible()"
            },
            "keyword": "Then "
          },
          {
            "result": {
              "duration": 15208249,
              "status": "passed"
            },
            "line": 12,
            "name": "the \u0027Pricing\u0027 nevbar menuitem is visible",
            "match": {
              "location": "homePage.the_Pricing_nevbar_menuitem_is_visible()"
            },
            "keyword": "Then "
          },
          {
            "result": {
              "duration": 13146333,
              "status": "passed"
            },
            "line": 13,
            "name": "the \u0027Why us?\u0027 nevbar menuitem is visible",
            "match": {
              "location": "homePage.the_Why_us_nevbar_menuitem_is_visible()"
            },
            "keyword": "Then "
          }
        ],
        "tags": [
          {
            "line": 4,
            "name": "@Verify_menuitems_visible_in_homepage_desktop"
          }
        ]
      }
    ],
    "name": "OTI Homepage Validation",
    "description": "",
    "id": "oti-homepage-validation",
    "keyword": "Feature",
    "uri": "verifyhompage_menuitems.feature",
    "tags": [
      {
        "line": 1,
        "name": "@Home_Page_MenuItem_Validation"
      }
    ]
  }
]